<?xml version="1.0" encoding="UTF-8" standalone="yes"?>
<p:sld xmlns:a="http://schemas.openxmlformats.org/drawingml/2006/main" xmlns:r="http://schemas.openxmlformats.org/officeDocument/2006/relationships" xmlns:p="http://schemas.openxmlformats.org/presentationml/2006/main"><p:cSld><p:bg><p:bgPr><a:blipFill dpi="0" rotWithShape="1"><a:blip r:embed="rId4"><a:lum/></a:blip><a:srcRect/><a:stretch><a:fillRect/></a:stretch></a:blipFill><a:effectLst/></p:bgPr></p:bg><p:spTree><p:nvGrpSpPr><p:cNvPr id="1" name=""/><p:cNvGrpSpPr/><p:nvPr/></p:nvGrpSpPr><p:grpSpPr><a:xfrm><a:off x="0" y="0"/><a:ext cx="0" cy="0"/><a:chOff x="0" y="0"/><a:chExt cx="0" cy="0"/></a:xfrm></p:grpSpPr><p:pic><p:nvPicPr><p:cNvPr id="55" name="Yellow Puck 5-1"/><p:cNvPicPr><a:picLocks noChangeAspect="1"/></p:cNvPicPr><p:nvPr/></p:nvPicPr><p:blipFill><a:blip r:embed="rId5"/><a:stretch><a:fillRect/></a:stretch></p:blipFill><p:spPr><a:xfrm><a:off x="7349161" y="4764845"/><a:ext cx="951058" cy="768163"/></a:xfrm><a:prstGeom prst="rect"><a:avLst/></a:prstGeom></p:spPr></p:pic><p:pic><p:nvPicPr><p:cNvPr id="3" name="Game Board"/><p:cNvPicPr><a:picLocks noChangeAspect="1"/></p:cNvPicPr><p:nvPr/></p:nvPicPr><p:blipFill><a:blip r:embed="rId6"/><a:stretch><a:fillRect/></a:stretch></p:blipFill><p:spPr><a:xfrm><a:off x="-1057" y="0"/><a:ext cx="12193057" cy="6858594"/></a:xfrm><a:prstGeom prst="rect"><a:avLst/></a:prstGeom></p:spPr></p:pic><p:sp><p:nvSpPr><p:cNvPr id="262" name="TextBox 1"/><p:cNvSpPr txBox="1"/><p:nvPr/></p:nvSpPr><p:spPr><a:xfrm><a:off x="163487" y="6039532"/><a:ext cx="1505175" cy="704167"/></a:xfrm><a:prstGeom prst="rect"><a:avLst/></a:prstGeom><a:noFill/></p:spPr><p:txBody><a:bodyPr wrap="square" rtlCol="0" anchor="ctr"><a:spAutoFit/></a:bodyPr><a:lstStyle/><a:p><a:pPr algn="ctr"><a:lnSpc><a:spcPct val="70000"/></a:lnSpc></a:pPr><a:r><a:rPr lang="en-US" sz="2800" dirty="0" smtClean="0"><a:solidFill><a:srgbClr val="0E4374"/></a:solidFill><a:latin typeface="LasVegas Jackpot" pitchFamily="50" charset="0"/></a:rPr><a:t>r</a:t></a:r><a:endParaRPr lang="en-US" sz="2800" dirty="0"><a:solidFill><a:srgbClr val="0E4374"/></a:solidFill><a:latin typeface="LasVegas Jackpot" pitchFamily="50" charset="0"/></a:endParaRPr></a:p></p:txBody></p:sp><p:sp><p:nvSpPr><p:cNvPr id="263" name="TextBox 2"/><p:cNvSpPr txBox="1"/><p:nvPr/></p:nvSpPr><p:spPr><a:xfrm><a:off x="1888043" y="6039532"/><a:ext cx="1505175" cy="704167"/></a:xfrm><a:prstGeom prst="rect"><a:avLst/></a:prstGeom><a:noFill/></p:spPr><p:txBody><a:bodyPr wrap="square" rtlCol="0" anchor="ctr"><a:spAutoFit/></a:bodyPr><a:lstStyle/><a:p><a:pPr algn="ctr"><a:lnSpc><a:spcPct val="70000"/></a:lnSpc></a:pPr><a:r><a:rPr lang="en-US" sz="2800" dirty="0" smtClean="0"><a:solidFill><a:srgbClr val="0E4374"/></a:solidFill><a:latin typeface="LasVegas Jackpot" pitchFamily="50" charset="0"/></a:rPr><a:t>picture/text goes here</a:t></a:r><a:endParaRPr lang="en-US" sz="2800" dirty="0"><a:solidFill><a:srgbClr val="0E4374"/></a:solidFill><a:latin typeface="LasVegas Jackpot" pitchFamily="50" charset="0"/></a:endParaRPr></a:p></p:txBody></p:sp><p:sp><p:nvSpPr><p:cNvPr id="264" name="TextBox 3"/><p:cNvSpPr txBox="1"/><p:nvPr/></p:nvSpPr><p:spPr><a:xfrm><a:off x="3613779" y="6039532"/><a:ext cx="1505175" cy="704167"/></a:xfrm><a:prstGeom prst="rect"><a:avLst/></a:prstGeom><a:noFill/></p:spPr><p:txBody><a:bodyPr wrap="square" rtlCol="0" anchor="ctr"><a:spAutoFit/></a:bodyPr><a:lstStyle/><a:p><a:pPr algn="ctr"><a:lnSpc><a:spcPct val="70000"/></a:lnSpc></a:pPr><a:r><a:rPr lang="en-US" sz="2800" dirty="0" smtClean="0"><a:solidFill><a:srgbClr val="0E4374"/></a:solidFill><a:latin typeface="LasVegas Jackpot" pitchFamily="50" charset="0"/></a:rPr><a:t>picture/text goes here</a:t></a:r><a:endParaRPr lang="en-US" sz="2800" dirty="0"><a:solidFill><a:srgbClr val="0E4374"/></a:solidFill><a:latin typeface="LasVegas Jackpot" pitchFamily="50" charset="0"/></a:endParaRPr></a:p></p:txBody></p:sp><p:sp><p:nvSpPr><p:cNvPr id="265" name="TextBox 4"/><p:cNvSpPr txBox="1"/><p:nvPr/></p:nvSpPr><p:spPr><a:xfrm><a:off x="5343940" y="6039532"/><a:ext cx="1505175" cy="704167"/></a:xfrm><a:prstGeom prst="rect"><a:avLst/></a:prstGeom><a:noFill/></p:spPr><p:txBody><a:bodyPr wrap="square" rtlCol="0" anchor="ctr"><a:spAutoFit/></a:bodyPr><a:lstStyle/><a:p><a:pPr algn="ctr"><a:lnSpc><a:spcPct val="70000"/></a:lnSpc></a:pPr><a:r><a:rPr lang="en-US" sz="2800" dirty="0" smtClean="0"><a:solidFill><a:srgbClr val="0E4374"/></a:solidFill><a:latin typeface="LasVegas Jackpot" pitchFamily="50" charset="0"/></a:rPr><a:t>picture/text goes here</a:t></a:r><a:endParaRPr lang="en-US" sz="2800" dirty="0"><a:solidFill><a:srgbClr val="0E4374"/></a:solidFill><a:latin typeface="LasVegas Jackpot" pitchFamily="50" charset="0"/></a:endParaRPr></a:p></p:txBody></p:sp><p:sp><p:nvSpPr><p:cNvPr id="266" name="TextBox 5"/><p:cNvSpPr txBox="1"/><p:nvPr/></p:nvSpPr><p:spPr><a:xfrm><a:off x="7047468" y="6039532"/><a:ext cx="1505175" cy="704167"/></a:xfrm><a:prstGeom prst="rect"><a:avLst/></a:prstGeom><a:noFill/></p:spPr><p:txBody><a:bodyPr wrap="square" rtlCol="0" anchor="ctr"><a:spAutoFit/></a:bodyPr><a:lstStyle/><a:p><a:pPr algn="ctr"><a:lnSpc><a:spcPct val="70000"/></a:lnSpc></a:pPr><a:r><a:rPr lang="en-US" sz="2800" dirty="0" smtClean="0"><a:solidFill><a:srgbClr val="0E4374"/></a:solidFill><a:latin typeface="LasVegas Jackpot" pitchFamily="50" charset="0"/></a:rPr><a:t>picture/text goes here</a:t></a:r><a:endParaRPr lang="en-US" sz="2800" dirty="0"><a:solidFill><a:srgbClr val="0E4374"/></a:solidFill><a:latin typeface="LasVegas Jackpot" pitchFamily="50" charset="0"/></a:endParaRPr></a:p></p:txBody></p:sp><p:sp><p:nvSpPr><p:cNvPr id="267" name="TextBox 6"/><p:cNvSpPr txBox="1"/><p:nvPr/></p:nvSpPr><p:spPr><a:xfrm><a:off x="8790132" y="6039532"/><a:ext cx="1505175" cy="704167"/></a:xfrm><a:prstGeom prst="rect"><a:avLst/></a:prstGeom><a:noFill/></p:spPr><p:txBody><a:bodyPr wrap="square" rtlCol="0" anchor="ctr"><a:spAutoFit/></a:bodyPr><a:lstStyle/><a:p><a:pPr algn="ctr"><a:lnSpc><a:spcPct val="70000"/></a:lnSpc></a:pPr><a:r><a:rPr lang="en-US" sz="2800" dirty="0" smtClean="0"><a:solidFill><a:srgbClr val="0E4374"/></a:solidFill><a:latin typeface="LasVegas Jackpot" pitchFamily="50" charset="0"/></a:rPr><a:t>picture/text goes here</a:t></a:r><a:endParaRPr lang="en-US" sz="2800" dirty="0"><a:solidFill><a:srgbClr val="0E4374"/></a:solidFill><a:latin typeface="LasVegas Jackpot" pitchFamily="50" charset="0"/></a:endParaRPr></a:p></p:txBody></p:sp><p:sp><p:nvSpPr><p:cNvPr id="268" name="TextBox 7"/><p:cNvSpPr txBox="1"/><p:nvPr/></p:nvSpPr><p:spPr><a:xfrm><a:off x="10506554" y="6039532"/><a:ext cx="1505175" cy="704167"/></a:xfrm><a:prstGeom prst="rect"><a:avLst/></a:prstGeom><a:noFill/></p:spPr><p:txBody><a:bodyPr wrap="square" rtlCol="0" anchor="ctr"><a:spAutoFit/></a:bodyPr><a:lstStyle/><a:p><a:pPr algn="ctr"><a:lnSpc><a:spcPct val="70000"/></a:lnSpc></a:pPr><a:r><a:rPr lang="en-US" sz="2800" dirty="0" smtClean="0"><a:solidFill><a:srgbClr val="0E4374"/></a:solidFill><a:latin typeface="LasVegas Jackpot" pitchFamily="50" charset="0"/></a:rPr><a:t>picture/text goes here</a:t></a:r><a:endParaRPr lang="en-US" sz="2800" dirty="0"><a:solidFill><a:srgbClr val="0E4374"/></a:solidFill><a:latin typeface="LasVegas Jackpot" pitchFamily="50" charset="0"/></a:endParaRPr></a:p></p:txBody></p:sp><p:sp><p:nvSpPr><p:cNvPr id="127" name="Yellow Button 7-1"/><p:cNvSpPr/><p:nvPr/></p:nvSpPr><p:spPr><a:xfrm rot="8578770"><a:off x="10880327" y="5681586"/><a:ext cx="350497" cy="350497"/></a:xfrm><a:prstGeom prst="chord"><a:avLst><a:gd name="adj1" fmla="val 2700000"/><a:gd name="adj2" fmla="val 12597475"/></a:avLst></a:prstGeom><a:solidFill><a:schemeClr val="accent5"/></a:solidFill><a:ln w="38100"><a:solidFill><a:schemeClr val="accent5"><a:lumMod val="40000"/><a:lumOff val="60000"/></a:schemeClr></a:solidFill></a:ln></p:spPr><p:style><a:lnRef idx="2"><a:schemeClr val="accent1"><a:shade val="50000"/></a:schemeClr></a:lnRef><a:fillRef idx="1"><a:schemeClr val="accent1"/></a:fillRef><a:effectRef idx="0"><a:schemeClr val="accent1"/></a:effectRef><a:fontRef idx="minor"><a:schemeClr val="lt1"/></a:fontRef></p:style><p:txBody><a:bodyPr rtlCol="0" anchor="ctr"/><a:lstStyle/><a:p><a:pPr algn="ctr"/><a:endParaRPr lang="en-US"/></a:p></p:txBody></p:sp><p:sp><p:nvSpPr><p:cNvPr id="128" name="Red Button 7-1"/><p:cNvSpPr/><p:nvPr/></p:nvSpPr><p:spPr><a:xfrm rot="8578770"><a:off x="11286264" y="5681586"/><a:ext cx="350497" cy="350497"/></a:xfrm><a:prstGeom prst="chord"><a:avLst><a:gd name="adj1" fmla="val 2700000"/><a:gd name="adj2" fmla="val 12597475"/></a:avLst></a:prstGeom><a:solidFill><a:srgbClr val="F34813"/></a:solidFill><a:ln w="38100"><a:solidFill><a:srgbClr val="F78663"/></a:solidFill></a:ln></p:spPr><p:style><a:lnRef idx="2"><a:schemeClr val="accent1"><a:shade val="50000"/></a:schemeClr></a:lnRef><a:fillRef idx="1"><a:schemeClr val="accent1"/></a:fillRef><a:effectRef idx="0"><a:schemeClr val="accent1"/></a:effectRef><a:fontRef idx="minor"><a:schemeClr val="lt1"/></a:fontRef></p:style><p:txBody><a:bodyPr rtlCol="0" anchor="ctr"/><a:lstStyle/><a:p><a:pPr algn="ctr"/><a:endParaRPr lang="en-US"/></a:p></p:txBody></p:sp><p:sp><p:nvSpPr><p:cNvPr id="129" name="Yellow Button 6-1"/><p:cNvSpPr/><p:nvPr/></p:nvSpPr><p:spPr><a:xfrm rot="8578770"><a:off x="9163289" y="5681586"/><a:ext cx="350497" cy="350497"/></a:xfrm><a:prstGeom prst="chord"><a:avLst><a:gd name="adj1" fmla="val 2700000"/><a:gd name="adj2" fmla="val 12597475"/></a:avLst></a:prstGeom><a:solidFill><a:schemeClr val="accent5"/></a:solidFill><a:ln w="38100"><a:solidFill><a:schemeClr val="accent5"><a:lumMod val="40000"/><a:lumOff val="60000"/></a:schemeClr></a:solidFill></a:ln></p:spPr><p:style><a:lnRef idx="2"><a:schemeClr val="accent1"><a:shade val="50000"/></a:schemeClr></a:lnRef><a:fillRef idx="1"><a:schemeClr val="accent1"/></a:fillRef><a:effectRef idx="0"><a:schemeClr val="accent1"/></a:effectRef><a:fontRef idx="minor"><a:schemeClr val="lt1"/></a:fontRef></p:style><p:txBody><a:bodyPr rtlCol="0" anchor="ctr"/><a:lstStyle/><a:p><a:pPr algn="ctr"/><a:endParaRPr lang="en-US"/></a:p></p:txBody></p:sp><p:sp><p:nvSpPr><p:cNvPr id="130" name="Red Button 6-1"/><p:cNvSpPr/><p:nvPr/></p:nvSpPr><p:spPr><a:xfrm rot="8578770"><a:off x="9569226" y="5681586"/><a:ext cx="350497" cy="350497"/></a:xfrm><a:prstGeom prst="chord"><a:avLst><a:gd name="adj1" fmla="val 2700000"/><a:gd name="adj2" fmla="val 12597475"/></a:avLst></a:prstGeom><a:solidFill><a:srgbClr val="F34813"/></a:solidFill><a:ln w="38100"><a:solidFill><a:srgbClr val="F78663"/></a:solidFill></a:ln></p:spPr><p:style><a:lnRef idx="2"><a:schemeClr val="accent1"><a:shade val="50000"/></a:schemeClr></a:lnRef><a:fillRef idx="1"><a:schemeClr val="accent1"/></a:fillRef><a:effectRef idx="0"><a:schemeClr val="accent1"/></a:effectRef><a:fontRef idx="minor"><a:schemeClr val="lt1"/></a:fontRef></p:style><p:txBody><a:bodyPr rtlCol="0" anchor="ctr"/><a:lstStyle/><a:p><a:pPr algn="ctr"/><a:endParaRPr lang="en-US"/></a:p></p:txBody></p:sp><p:sp><p:nvSpPr><p:cNvPr id="131" name="Yellow Button 5-1"/><p:cNvSpPr/><p:nvPr/></p:nvSpPr><p:spPr><a:xfrm rot="8578770"><a:off x="7437553" y="5681586"/><a:ext cx="350497" cy="350497"/></a:xfrm><a:prstGeom prst="chord"><a:avLst><a:gd name="adj1" fmla="val 2700000"/><a:gd name="adj2" fmla="val 12597475"/></a:avLst></a:prstGeom><a:solidFill><a:schemeClr val="accent5"/></a:solidFill><a:ln w="38100"><a:solidFill><a:schemeClr val="accent5"><a:lumMod val="40000"/><a:lumOff val="60000"/></a:schemeClr></a:solidFill></a:ln></p:spPr><p:style><a:lnRef idx="2"><a:schemeClr val="accent1"><a:shade val="50000"/></a:schemeClr></a:lnRef><a:fillRef idx="1"><a:schemeClr val="accent1"/></a:fillRef><a:effectRef idx="0"><a:schemeClr val="accent1"/></a:effectRef><a:fontRef idx="minor"><a:schemeClr val="lt1"/></a:fontRef></p:style><p:txBody><a:bodyPr rtlCol="0" anchor="ctr"/><a:lstStyle/><a:p><a:pPr algn="ctr"/><a:endParaRPr lang="en-US"/></a:p></p:txBody></p:sp><p:sp><p:nvSpPr><p:cNvPr id="132" name="Red Button 5-1"/><p:cNvSpPr/><p:nvPr/></p:nvSpPr><p:spPr><a:xfrm rot="8578770"><a:off x="7843490" y="5681586"/><a:ext cx="350497" cy="350497"/></a:xfrm><a:prstGeom prst="chord"><a:avLst><a:gd name="adj1" fmla="val 2700000"/><a:gd name="adj2" fmla="val 12597475"/></a:avLst></a:prstGeom><a:solidFill><a:srgbClr val="F34813"/></a:solidFill><a:ln w="38100"><a:solidFill><a:srgbClr val="F78663"/></a:solidFill></a:ln></p:spPr><p:style><a:lnRef idx="2"><a:schemeClr val="accent1"><a:shade val="50000"/></a:schemeClr></a:lnRef><a:fillRef idx="1"><a:schemeClr val="accent1"/></a:fillRef><a:effectRef idx="0"><a:schemeClr val="accent1"/></a:effectRef><a:fontRef idx="minor"><a:schemeClr val="lt1"/></a:fontRef></p:style><p:txBody><a:bodyPr rtlCol="0" anchor="ctr"/><a:lstStyle/><a:p><a:pPr algn="ctr"/><a:endParaRPr lang="en-US"/></a:p></p:txBody></p:sp><p:sp><p:nvSpPr><p:cNvPr id="133" name="Yellow Button 4-1"/><p:cNvSpPr/><p:nvPr/></p:nvSpPr><p:spPr><a:xfrm rot="8578770"><a:off x="5711816" y="5681586"/><a:ext cx="350497" cy="350497"/></a:xfrm><a:prstGeom prst="chord"><a:avLst><a:gd name="adj1" fmla="val 2700000"/><a:gd name="adj2" fmla="val 12597475"/></a:avLst></a:prstGeom><a:solidFill><a:schemeClr val="accent5"/></a:solidFill><a:ln w="38100"><a:solidFill><a:schemeClr val="accent5"><a:lumMod val="40000"/><a:lumOff val="60000"/></a:schemeClr></a:solidFill></a:ln></p:spPr><p:style><a:lnRef idx="2"><a:schemeClr val="accent1"><a:shade val="50000"/></a:schemeClr></a:lnRef><a:fillRef idx="1"><a:schemeClr val="accent1"/></a:fillRef><a:effectRef idx="0"><a:schemeClr val="accent1"/></a:effectRef><a:fontRef idx="minor"><a:schemeClr val="lt1"/></a:fontRef></p:style><p:txBody><a:bodyPr rtlCol="0" anchor="ctr"/><a:lstStyle/><a:p><a:pPr algn="ctr"/><a:endParaRPr lang="en-US"/></a:p></p:txBody></p:sp><p:sp><p:nvSpPr><p:cNvPr id="134" name="Red Button 4-1"/><p:cNvSpPr/><p:nvPr/></p:nvSpPr><p:spPr><a:xfrm rot="8578770"><a:off x="6117753" y="5681586"/><a:ext cx="350497" cy="350497"/></a:xfrm><a:prstGeom prst="chord"><a:avLst><a:gd name="adj1" fmla="val 2700000"/><a:gd name="adj2" fmla="val 12597475"/></a:avLst></a:prstGeom><a:solidFill><a:srgbClr val="F34813"/></a:solidFill><a:ln w="38100"><a:solidFill><a:srgbClr val="F78663"/></a:solidFill></a:ln></p:spPr><p:style><a:lnRef idx="2"><a:schemeClr val="accent1"><a:shade val="50000"/></a:schemeClr></a:lnRef><a:fillRef idx="1"><a:schemeClr val="accent1"/></a:fillRef><a:effectRef idx="0"><a:schemeClr val="accent1"/></a:effectRef><a:fontRef idx="minor"><a:schemeClr val="lt1"/></a:fontRef></p:style><p:txBody><a:bodyPr rtlCol="0" anchor="ctr"/><a:lstStyle/><a:p><a:pPr algn="ctr"/><a:endParaRPr lang="en-US"/></a:p></p:txBody></p:sp><p:sp><p:nvSpPr><p:cNvPr id="135" name="Yellow Button 3-1"/><p:cNvSpPr/><p:nvPr/></p:nvSpPr><p:spPr><a:xfrm rot="8578770"><a:off x="3986547" y="5681586"/><a:ext cx="350497" cy="350497"/></a:xfrm><a:prstGeom prst="chord"><a:avLst><a:gd name="adj1" fmla="val 2700000"/><a:gd name="adj2" fmla="val 12597475"/></a:avLst></a:prstGeom><a:solidFill><a:schemeClr val="accent5"/></a:solidFill><a:ln w="38100"><a:solidFill><a:schemeClr val="accent5"><a:lumMod val="40000"/><a:lumOff val="60000"/></a:schemeClr></a:solidFill></a:ln></p:spPr><p:style><a:lnRef idx="2"><a:schemeClr val="accent1"><a:shade val="50000"/></a:schemeClr></a:lnRef><a:fillRef idx="1"><a:schemeClr val="accent1"/></a:fillRef><a:effectRef idx="0"><a:schemeClr val="accent1"/></a:effectRef><a:fontRef idx="minor"><a:schemeClr val="lt1"/></a:fontRef></p:style><p:txBody><a:bodyPr rtlCol="0" anchor="ctr"/><a:lstStyle/><a:p><a:pPr algn="ctr"/><a:endParaRPr lang="en-US"/></a:p></p:txBody></p:sp><p:sp><p:nvSpPr><p:cNvPr id="136" name="Red Button 3-1"/><p:cNvSpPr/><p:nvPr/></p:nvSpPr><p:spPr><a:xfrm rot="8578770"><a:off x="4392484" y="5681586"/><a:ext cx="350497" cy="350497"/></a:xfrm><a:prstGeom prst="chord"><a:avLst><a:gd name="adj1" fmla="val 2700000"/><a:gd name="adj2" fmla="val 12597475"/></a:avLst></a:prstGeom><a:solidFill><a:srgbClr val="F34813"/></a:solidFill><a:ln w="38100"><a:solidFill><a:srgbClr val="F78663"/></a:solidFill></a:ln></p:spPr><p:style><a:lnRef idx="2"><a:schemeClr val="accent1"><a:shade val="50000"/></a:schemeClr></a:lnRef><a:fillRef idx="1"><a:schemeClr val="accent1"/></a:fillRef><a:effectRef idx="0"><a:schemeClr val="accent1"/></a:effectRef><a:fontRef idx="minor"><a:schemeClr val="lt1"/></a:fontRef></p:style><p:txBody><a:bodyPr rtlCol="0" anchor="ctr"/><a:lstStyle/><a:p><a:pPr algn="ctr"/><a:endParaRPr lang="en-US"/></a:p></p:txBody></p:sp><p:sp><p:nvSpPr><p:cNvPr id="137" name="Yellow Button 2-1"/><p:cNvSpPr/><p:nvPr/></p:nvSpPr><p:spPr><a:xfrm rot="8578770"><a:off x="2260346" y="5681586"/><a:ext cx="350497" cy="350497"/></a:xfrm><a:prstGeom prst="chord"><a:avLst><a:gd name="adj1" fmla="val 2700000"/><a:gd name="adj2" fmla="val 12597475"/></a:avLst></a:prstGeom><a:solidFill><a:schemeClr val="accent5"/></a:solidFill><a:ln w="38100"><a:solidFill><a:schemeClr val="accent5"><a:lumMod val="40000"/><a:lumOff val="60000"/></a:schemeClr></a:solidFill></a:ln></p:spPr><p:style><a:lnRef idx="2"><a:schemeClr val="accent1"><a:shade val="50000"/></a:schemeClr></a:lnRef><a:fillRef idx="1"><a:schemeClr val="accent1"/></a:fillRef><a:effectRef idx="0"><a:schemeClr val="accent1"/></a:effectRef><a:fontRef idx="minor"><a:schemeClr val="lt1"/></a:fontRef></p:style><p:txBody><a:bodyPr rtlCol="0" anchor="ctr"/><a:lstStyle/><a:p><a:pPr algn="ctr"/><a:endParaRPr lang="en-US"/></a:p></p:txBody></p:sp><p:sp><p:nvSpPr><p:cNvPr id="138" name="Red Button 2-1"/><p:cNvSpPr/><p:nvPr/></p:nvSpPr><p:spPr><a:xfrm rot="8578770"><a:off x="2666283" y="5681586"/><a:ext cx="350497" cy="350497"/></a:xfrm><a:prstGeom prst="chord"><a:avLst><a:gd name="adj1" fmla="val 2700000"/><a:gd name="adj2" fmla="val 12597475"/></a:avLst></a:prstGeom><a:solidFill><a:srgbClr val="F34813"/></a:solidFill><a:ln w="38100"><a:solidFill><a:srgbClr val="F78663"/></a:solidFill></a:ln></p:spPr><p:style><a:lnRef idx="2"><a:schemeClr val="accent1"><a:shade val="50000"/></a:schemeClr></a:lnRef><a:fillRef idx="1"><a:schemeClr val="accent1"/></a:fillRef><a:effectRef idx="0"><a:schemeClr val="accent1"/></a:effectRef><a:fontRef idx="minor"><a:schemeClr val="lt1"/></a:fontRef></p:style><p:txBody><a:bodyPr rtlCol="0" anchor="ctr"/><a:lstStyle/><a:p><a:pPr algn="ctr"/><a:endParaRPr lang="en-US"/></a:p></p:txBody></p:sp><p:sp><p:nvSpPr><p:cNvPr id="139" name="Yellow Button 1-1"/><p:cNvSpPr/><p:nvPr/></p:nvSpPr><p:spPr><a:xfrm rot="8578770"><a:off x="534610" y="5681586"/><a:ext cx="350497" cy="350497"/></a:xfrm><a:prstGeom prst="chord"><a:avLst><a:gd name="adj1" fmla="val 2700000"/><a:gd name="adj2" fmla="val 12597475"/></a:avLst></a:prstGeom><a:solidFill><a:schemeClr val="accent5"/></a:solidFill><a:ln w="38100"><a:solidFill><a:schemeClr val="accent5"><a:lumMod val="40000"/><a:lumOff val="60000"/></a:schemeClr></a:solidFill></a:ln></p:spPr><p:style><a:lnRef idx="2"><a:schemeClr val="accent1"><a:shade val="50000"/></a:schemeClr></a:lnRef><a:fillRef idx="1"><a:schemeClr val="accent1"/></a:fillRef><a:effectRef idx="0"><a:schemeClr val="accent1"/></a:effectRef><a:fontRef idx="minor"><a:schemeClr val="lt1"/></a:fontRef></p:style><p:txBody><a:bodyPr rtlCol="0" anchor="ctr"/><a:lstStyle/><a:p><a:pPr algn="ctr"/><a:endParaRPr lang="en-US"/></a:p></p:txBody></p:sp><p:sp><p:nvSpPr><p:cNvPr id="140" name="Red Button 1-1"/><p:cNvSpPr/><p:nvPr/></p:nvSpPr><p:spPr><a:xfrm rot="8578770"><a:off x="940547" y="5681586"/><a:ext cx="350497" cy="350497"/></a:xfrm><a:prstGeom prst="chord"><a:avLst><a:gd name="adj1" fmla="val 2700000"/><a:gd name="adj2" fmla="val 12597475"/></a:avLst></a:prstGeom><a:solidFill><a:srgbClr val="F34813"/></a:solidFill><a:ln w="38100"><a:solidFill><a:srgbClr val="F78663"/></a:solidFill></a:ln></p:spPr><p:style><a:lnRef idx="2"><a:schemeClr val="accent1"><a:shade val="50000"/></a:schemeClr></a:lnRef><a:fillRef idx="1"><a:schemeClr val="accent1"/></a:fillRef><a:effectRef idx="0"><a:schemeClr val="accent1"/></a:effectRef><a:fontRef idx="minor"><a:schemeClr val="lt1"/></a:fontRef></p:style><p:txBody><a:bodyPr rtlCol="0" anchor="ctr"/><a:lstStyle/><a:p><a:pPr algn="ctr"/><a:endParaRPr lang="en-US"/></a:p></p:txBody></p:sp><p:sp><p:nvSpPr><p:cNvPr id="5" name="Arrow 1"/><p:cNvSpPr/><p:nvPr/></p:nvSpPr><p:spPr><a:xfrm><a:off x="590385" y="5114759"/><a:ext cx="651377" cy="924773"/></a:xfrm><a:prstGeom prst="downArrow"><a:avLst/></a:prstGeom><a:solidFill><a:srgbClr val="92D050"/></a:solidFill><a:ln w="38100"><a:solidFill><a:schemeClr val="bg1"/></a:solidFill></a:ln></p:spPr><p:style><a:lnRef idx="2"><a:schemeClr val="accent1"><a:shade val="50000"/></a:schemeClr></a:lnRef><a:fillRef idx="1"><a:schemeClr val="accent1"/></a:fillRef><a:effectRef idx="0"><a:schemeClr val="accent1"/></a:effectRef><a:fontRef idx="minor"><a:schemeClr val="lt1"/></a:fontRef></p:style><p:txBody><a:bodyPr rtlCol="0" anchor="ctr"/><a:lstStyle/><a:p><a:pPr algn="ctr"/><a:endParaRPr lang="en-US"/></a:p></p:txBody></p:sp><p:sp><p:nvSpPr><p:cNvPr id="234" name="Arrow 2"/><p:cNvSpPr/><p:nvPr/></p:nvSpPr><p:spPr><a:xfrm><a:off x="2306742" y="5114759"/><a:ext cx="651377" cy="924773"/></a:xfrm><a:prstGeom prst="downArrow"><a:avLst/></a:prstGeom><a:solidFill><a:srgbClr val="92D050"/></a:solidFill><a:ln w="38100"><a:solidFill><a:schemeClr val="bg1"/></a:solidFill></a:ln></p:spPr><p:style><a:lnRef idx="2"><a:schemeClr val="accent1"><a:shade val="50000"/></a:schemeClr></a:lnRef><a:fillRef idx="1"><a:schemeClr val="accent1"/></a:fillRef><a:effectRef idx="0"><a:schemeClr val="accent1"/></a:effectRef><a:fontRef idx="minor"><a:schemeClr val="lt1"/></a:fontRef></p:style><p:txBody><a:bodyPr rtlCol="0" anchor="ctr"/><a:lstStyle/><a:p><a:pPr algn="ctr"/><a:endParaRPr lang="en-US"/></a:p></p:txBody></p:sp><p:sp><p:nvSpPr><p:cNvPr id="237" name="Arrow 3"/><p:cNvSpPr/><p:nvPr/></p:nvSpPr><p:spPr><a:xfrm><a:off x="4036111" y="5114759"/><a:ext cx="651377" cy="924773"/></a:xfrm><a:prstGeom prst="downArrow"><a:avLst/></a:prstGeom><a:solidFill><a:srgbClr val="92D050"/></a:solidFill><a:ln w="38100"><a:solidFill><a:schemeClr val="bg1"/></a:solidFill></a:ln></p:spPr><p:style><a:lnRef idx="2"><a:schemeClr val="accent1"><a:shade val="50000"/></a:schemeClr></a:lnRef><a:fillRef idx="1"><a:schemeClr val="accent1"/></a:fillRef><a:effectRef idx="0"><a:schemeClr val="accent1"/></a:effectRef><a:fontRef idx="minor"><a:schemeClr val="lt1"/></a:fontRef></p:style><p:txBody><a:bodyPr rtlCol="0" anchor="ctr"/><a:lstStyle/><a:p><a:pPr algn="ctr"/><a:endParaRPr lang="en-US"/></a:p></p:txBody></p:sp><p:sp><p:nvSpPr><p:cNvPr id="240" name="Arrow 4"/><p:cNvSpPr/><p:nvPr/></p:nvSpPr><p:spPr><a:xfrm><a:off x="5764344" y="5114759"/><a:ext cx="651377" cy="924773"/></a:xfrm><a:prstGeom prst="downArrow"><a:avLst/></a:prstGeom><a:solidFill><a:srgbClr val="92D050"/></a:solidFill><a:ln w="38100"><a:solidFill><a:schemeClr val="bg1"/></a:solidFill></a:ln></p:spPr><p:style><a:lnRef idx="2"><a:schemeClr val="accent1"><a:shade val="50000"/></a:schemeClr></a:lnRef><a:fillRef idx="1"><a:schemeClr val="accent1"/></a:fillRef><a:effectRef idx="0"><a:schemeClr val="accent1"/></a:effectRef><a:fontRef idx="minor"><a:schemeClr val="lt1"/></a:fontRef></p:style><p:txBody><a:bodyPr rtlCol="0" anchor="ctr"/><a:lstStyle/><a:p><a:pPr algn="ctr"/><a:endParaRPr lang="en-US"/></a:p></p:txBody></p:sp><p:sp><p:nvSpPr><p:cNvPr id="243" name="Arrow 5"/><p:cNvSpPr/><p:nvPr/></p:nvSpPr><p:spPr><a:xfrm><a:off x="7476452" y="5114759"/><a:ext cx="651377" cy="924773"/></a:xfrm><a:prstGeom prst="downArrow"><a:avLst/></a:prstGeom><a:solidFill><a:srgbClr val="92D050"/></a:solidFill><a:ln w="38100"><a:solidFill><a:schemeClr val="bg1"/></a:solidFill></a:ln></p:spPr><p:style><a:lnRef idx="2"><a:schemeClr val="accent1"><a:shade val="50000"/></a:schemeClr></a:lnRef><a:fillRef idx="1"><a:schemeClr val="accent1"/></a:fillRef><a:effectRef idx="0"><a:schemeClr val="accent1"/></a:effectRef><a:fontRef idx="minor"><a:schemeClr val="lt1"/></a:fontRef></p:style><p:txBody><a:bodyPr rtlCol="0" anchor="ctr"/><a:lstStyle/><a:p><a:pPr algn="ctr"/><a:endParaRPr lang="en-US"/></a:p></p:txBody></p:sp><p:sp><p:nvSpPr><p:cNvPr id="246" name="Arrow 6"/><p:cNvSpPr/><p:nvPr/></p:nvSpPr><p:spPr><a:xfrm><a:off x="9217176" y="5114759"/><a:ext cx="651377" cy="924773"/></a:xfrm><a:prstGeom prst="downArrow"><a:avLst/></a:prstGeom><a:solidFill><a:srgbClr val="92D050"/></a:solidFill><a:ln w="38100"><a:solidFill><a:schemeClr val="bg1"/></a:solidFill></a:ln></p:spPr><p:style><a:lnRef idx="2"><a:schemeClr val="accent1"><a:shade val="50000"/></a:schemeClr></a:lnRef><a:fillRef idx="1"><a:schemeClr val="accent1"/></a:fillRef><a:effectRef idx="0"><a:schemeClr val="accent1"/></a:effectRef><a:fontRef idx="minor"><a:schemeClr val="lt1"/></a:fontRef></p:style><p:txBody><a:bodyPr rtlCol="0" anchor="ctr"/><a:lstStyle/><a:p><a:pPr algn="ctr"/><a:endParaRPr lang="en-US"/></a:p></p:txBody></p:sp><p:sp><p:nvSpPr><p:cNvPr id="249" name="Arrow 7"/><p:cNvSpPr/><p:nvPr/></p:nvSpPr><p:spPr><a:xfrm><a:off x="10933453" y="5114759"/><a:ext cx="651377" cy="924773"/></a:xfrm><a:prstGeom prst="downArrow"><a:avLst/></a:prstGeom><a:solidFill><a:srgbClr val="92D050"/></a:solidFill><a:ln w="38100"><a:solidFill><a:schemeClr val="bg1"/></a:solidFill></a:ln></p:spPr><p:style><a:lnRef idx="2"><a:schemeClr val="accent1"><a:shade val="50000"/></a:schemeClr></a:lnRef><a:fillRef idx="1"><a:schemeClr val="accent1"/></a:fillRef><a:effectRef idx="0"><a:schemeClr val="accent1"/></a:effectRef><a:fontRef idx="minor"><a:schemeClr val="lt1"/></a:fontRef></p:style><p:txBody><a:bodyPr rtlCol="0" anchor="ctr"/><a:lstStyle/><a:p><a:pPr algn="ctr"/><a:endParaRPr lang="en-US"/></a:p></p:txBody></p:sp></p:spTree><p:extLst><p:ext uri="{BB962C8B-B14F-4D97-AF65-F5344CB8AC3E}"><p14:creationId xmlns:p14="http://schemas.microsoft.com/office/powerpoint/2010/main" val="1210355721"/></p:ext></p:extLst></p:cSld><p:clrMapOvr><a:masterClrMapping/></p:clrMapOvr><p:transition spd="med" advClick="0"><p:pull/></p:transition><mc:AlternateContent xmlns:mc="http://schemas.openxmlformats.org/markup-compatibility/2006" xmlns:p14="http://schemas.microsoft.com/office/powerpoint/2010/main"><mc:Choice Requires="p14"><p:timing><p:tnLst><p:par><p:cTn id="1" dur="indefinite" restart="never" nodeType="tmRoot"><p:childTnLst><p:seq concurrent="1" nextAc="seek"><p:cTn id="2" dur="indefinite" nodeType="mainSeq"><p:childTnLst><p:par><p:cTn id="3" fill="hold"><p:stCondLst><p:cond delay="indefinite"/><p:cond evt="onBegin" delay="0"><p:tn val="2"/></p:cond></p:stCondLst><p:childTnLst><p:par><p:cTn id="4" fill="hold"><p:stCondLst><p:cond delay="0"/></p:stCondLst><p:childTnLst><p:par><p:cTn id="5" presetID="47" presetClass="entr" presetSubtype="0" fill="hold" grpId="0" nodeType="withEffect"><p:stCondLst><p:cond delay="0"/></p:stCondLst><p:childTnLst><p:set><p:cBhvr><p:cTn id="6" dur="1" fill="hold"><p:stCondLst><p:cond delay="0"/></p:stCondLst></p:cTn><p:tgtEl><p:spTgt spid="5"/></p:tgtEl><p:attrNameLst><p:attrName>style.visibility</p:attrName></p:attrNameLst></p:cBhvr><p:to><p:strVal val="visible"/></p:to></p:set><p:animEffect transition="in" filter="fade"><p:cBhvr><p:cTn id="7" dur="1000"/><p:tgtEl><p:spTgt spid="5"/></p:tgtEl></p:cBhvr></p:animEffect><p:anim calcmode="lin" valueType="num"><p:cBhvr><p:cTn id="8" dur="1000" fill="hold"/><p:tgtEl><p:spTgt spid="5"/></p:tgtEl><p:attrNameLst><p:attrName>ppt_x</p:attrName></p:attrNameLst></p:cBhvr><p:tavLst><p:tav tm="0"><p:val><p:strVal val="#ppt_x"/></p:val></p:tav><p:tav tm="100000"><p:val><p:strVal val="#ppt_x"/></p:val></p:tav></p:tavLst></p:anim><p:anim calcmode="lin" valueType="num"><p:cBhvr><p:cTn id="9" dur="1000" fill="hold"/><p:tgtEl><p:spTgt spid="5"/></p:tgtEl><p:attrNameLst><p:attrName>ppt_y</p:attrName></p:attrNameLst></p:cBhvr><p:tavLst><p:tav tm="0"><p:val><p:strVal val="#ppt_y-.1"/></p:val></p:tav><p:tav tm="100000"><p:val><p:strVal val="#ppt_y"/></p:val></p:tav></p:tavLst></p:anim></p:childTnLst></p:cTn></p:par><p:par><p:cTn id="10" presetID="47" presetClass="entr" presetSubtype="0" fill="hold" grpId="0" nodeType="withEffect"><p:stCondLst><p:cond delay="0"/></p:stCondLst><p:childTnLst><p:set><p:cBhvr><p:cTn id="11" dur="1" fill="hold"><p:stCondLst><p:cond delay="0"/></p:stCondLst></p:cTn><p:tgtEl><p:spTgt spid="234"/></p:tgtEl><p:attrNameLst><p:attrName>style.visibility</p:attrName></p:attrNameLst></p:cBhvr><p:to><p:strVal val="visible"/></p:to></p:set><p:animEffect transition="in" filter="fade"><p:cBhvr><p:cTn id="12" dur="1000"/><p:tgtEl><p:spTgt spid="234"/></p:tgtEl></p:cBhvr></p:animEffect><p:anim calcmode="lin" valueType="num"><p:cBhvr><p:cTn id="13" dur="1000" fill="hold"/><p:tgtEl><p:spTgt spid="234"/></p:tgtEl><p:attrNameLst><p:attrName>ppt_x</p:attrName></p:attrNameLst></p:cBhvr><p:tavLst><p:tav tm="0"><p:val><p:strVal val="#ppt_x"/></p:val></p:tav><p:tav tm="100000"><p:val><p:strVal val="#ppt_x"/></p:val></p:tav></p:tavLst></p:anim><p:anim calcmode="lin" valueType="num"><p:cBhvr><p:cTn id="14" dur="1000" fill="hold"/><p:tgtEl><p:spTgt spid="234"/></p:tgtEl><p:attrNameLst><p:attrName>ppt_y</p:attrName></p:attrNameLst></p:cBhvr><p:tavLst><p:tav tm="0"><p:val><p:strVal val="#ppt_y-.1"/></p:val></p:tav><p:tav tm="100000"><p:val><p:strVal val="#ppt_y"/></p:val></p:tav></p:tavLst></p:anim></p:childTnLst></p:cTn></p:par><p:par><p:cTn id="15" presetID="47" presetClass="entr" presetSubtype="0" fill="hold" grpId="0" nodeType="withEffect"><p:stCondLst><p:cond delay="0"/></p:stCondLst><p:childTnLst><p:set><p:cBhvr><p:cTn id="16" dur="1" fill="hold"><p:stCondLst><p:cond delay="0"/></p:stCondLst></p:cTn><p:tgtEl><p:spTgt spid="237"/></p:tgtEl><p:attrNameLst><p:attrName>style.visibility</p:attrName></p:attrNameLst></p:cBhvr><p:to><p:strVal val="visible"/></p:to></p:set><p:animEffect transition="in" filter="fade"><p:cBhvr><p:cTn id="17" dur="1000"/><p:tgtEl><p:spTgt spid="237"/></p:tgtEl></p:cBhvr></p:animEffect><p:anim calcmode="lin" valueType="num"><p:cBhvr><p:cTn id="18" dur="1000" fill="hold"/><p:tgtEl><p:spTgt spid="237"/></p:tgtEl><p:attrNameLst><p:attrName>ppt_x</p:attrName></p:attrNameLst></p:cBhvr><p:tavLst><p:tav tm="0"><p:val><p:strVal val="#ppt_x"/></p:val></p:tav><p:tav tm="100000"><p:val><p:strVal val="#ppt_x"/></p:val></p:tav></p:tavLst></p:anim><p:anim calcmode="lin" valueType="num"><p:cBhvr><p:cTn id="19" dur="1000" fill="hold"/><p:tgtEl><p:spTgt spid="237"/></p:tgtEl><p:attrNameLst><p:attrName>ppt_y</p:attrName></p:attrNameLst></p:cBhvr><p:tavLst><p:tav tm="0"><p:val><p:strVal val="#ppt_y-.1"/></p:val></p:tav><p:tav tm="100000"><p:val><p:strVal val="#ppt_y"/></p:val></p:tav></p:tavLst></p:anim></p:childTnLst></p:cTn></p:par><p:par><p:cTn id="20" presetID="47" presetClass="entr" presetSubtype="0" fill="hold" grpId="0" nodeType="withEffect"><p:stCondLst><p:cond delay="0"/></p:stCondLst><p:childTnLst><p:set><p:cBhvr><p:cTn id="21" dur="1" fill="hold"><p:stCondLst><p:cond delay="0"/></p:stCondLst></p:cTn><p:tgtEl><p:spTgt spid="240"/></p:tgtEl><p:attrNameLst><p:attrName>style.visibility</p:attrName></p:attrNameLst></p:cBhvr><p:to><p:strVal val="visible"/></p:to></p:set><p:animEffect transition="in" filter="fade"><p:cBhvr><p:cTn id="22" dur="1000"/><p:tgtEl><p:spTgt spid="240"/></p:tgtEl></p:cBhvr></p:animEffect><p:anim calcmode="lin" valueType="num"><p:cBhvr><p:cTn id="23" dur="1000" fill="hold"/><p:tgtEl><p:spTgt spid="240"/></p:tgtEl><p:attrNameLst><p:attrName>ppt_x</p:attrName></p:attrNameLst></p:cBhvr><p:tavLst><p:tav tm="0"><p:val><p:strVal val="#ppt_x"/></p:val></p:tav><p:tav tm="100000"><p:val><p:strVal val="#ppt_x"/></p:val></p:tav></p:tavLst></p:anim><p:anim calcmode="lin" valueType="num"><p:cBhvr><p:cTn id="24" dur="1000" fill="hold"/><p:tgtEl><p:spTgt spid="240"/></p:tgtEl><p:attrNameLst><p:attrName>ppt_y</p:attrName></p:attrNameLst></p:cBhvr><p:tavLst><p:tav tm="0"><p:val><p:strVal val="#ppt_y-.1"/></p:val></p:tav><p:tav tm="100000"><p:val><p:strVal val="#ppt_y"/></p:val></p:tav></p:tavLst></p:anim></p:childTnLst></p:cTn></p:par><p:par><p:cTn id="25" presetID="47" presetClass="entr" presetSubtype="0" fill="hold" grpId="0" nodeType="withEffect"><p:stCondLst><p:cond delay="0"/></p:stCondLst><p:childTnLst><p:set><p:cBhvr><p:cTn id="26" dur="1" fill="hold"><p:stCondLst><p:cond delay="0"/></p:stCondLst></p:cTn><p:tgtEl><p:spTgt spid="243"/></p:tgtEl><p:attrNameLst><p:attrName>style.visibility</p:attrName></p:attrNameLst></p:cBhvr><p:to><p:strVal val="visible"/></p:to></p:set><p:animEffect transition="in" filter="fade"><p:cBhvr><p:cTn id="27" dur="1000"/><p:tgtEl><p:spTgt spid="243"/></p:tgtEl></p:cBhvr></p:animEffect><p:anim calcmode="lin" valueType="num"><p:cBhvr><p:cTn id="28" dur="1000" fill="hold"/><p:tgtEl><p:spTgt spid="243"/></p:tgtEl><p:attrNameLst><p:attrName>ppt_x</p:attrName></p:attrNameLst></p:cBhvr><p:tavLst><p:tav tm="0"><p:val><p:strVal val="#ppt_x"/></p:val></p:tav><p:tav tm="100000"><p:val><p:strVal val="#ppt_x"/></p:val></p:tav></p:tavLst></p:anim><p:anim calcmode="lin" valueType="num"><p:cBhvr><p:cTn id="29" dur="1000" fill="hold"/><p:tgtEl><p:spTgt spid="243"/></p:tgtEl><p:attrNameLst><p:attrName>ppt_y</p:attrName></p:attrNameLst></p:cBhvr><p:tavLst><p:tav tm="0"><p:val><p:strVal val="#ppt_y-.1"/></p:val></p:tav><p:tav tm="100000"><p:val><p:strVal val="#ppt_y"/></p:val></p:tav></p:tavLst></p:anim></p:childTnLst></p:cTn></p:par><p:par><p:cTn id="30" presetID="47" presetClass="entr" presetSubtype="0" fill="hold" grpId="0" nodeType="withEffect"><p:stCondLst><p:cond delay="0"/></p:stCondLst><p:childTnLst><p:set><p:cBhvr><p:cTn id="31" dur="1" fill="hold"><p:stCondLst><p:cond delay="0"/></p:stCondLst></p:cTn><p:tgtEl><p:spTgt spid="246"/></p:tgtEl><p:attrNameLst><p:attrName>style.visibility</p:attrName></p:attrNameLst></p:cBhvr><p:to><p:strVal val="visible"/></p:to></p:set><p:animEffect transition="in" filter="fade"><p:cBhvr><p:cTn id="32" dur="1000"/><p:tgtEl><p:spTgt spid="246"/></p:tgtEl></p:cBhvr></p:animEffect><p:anim calcmode="lin" valueType="num"><p:cBhvr><p:cTn id="33" dur="1000" fill="hold"/><p:tgtEl><p:spTgt spid="246"/></p:tgtEl><p:attrNameLst><p:attrName>ppt_x</p:attrName></p:attrNameLst></p:cBhvr><p:tavLst><p:tav tm="0"><p:val><p:strVal val="#ppt_x"/></p:val></p:tav><p:tav tm="100000"><p:val><p:strVal val="#ppt_x"/></p:val></p:tav></p:tavLst></p:anim><p:anim calcmode="lin" valueType="num"><p:cBhvr><p:cTn id="34" dur="1000" fill="hold"/><p:tgtEl><p:spTgt spid="246"/></p:tgtEl><p:attrNameLst><p:attrName>ppt_y</p:attrName></p:attrNameLst></p:cBhvr><p:tavLst><p:tav tm="0"><p:val><p:strVal val="#ppt_y-.1"/></p:val></p:tav><p:tav tm="100000"><p:val><p:strVal val="#ppt_y"/></p:val></p:tav></p:tavLst></p:anim></p:childTnLst></p:cTn></p:par><p:par><p:cTn id="35" presetID="47" presetClass="entr" presetSubtype="0" fill="hold" grpId="0" nodeType="withEffect"><p:stCondLst><p:cond delay="0"/></p:stCondLst><p:childTnLst><p:set><p:cBhvr><p:cTn id="36" dur="1" fill="hold"><p:stCondLst><p:cond delay="0"/></p:stCondLst></p:cTn><p:tgtEl><p:spTgt spid="249"/></p:tgtEl><p:attrNameLst><p:attrName>style.visibility</p:attrName></p:attrNameLst></p:cBhvr><p:to><p:strVal val="visible"/></p:to></p:set><p:animEffect transition="in" filter="fade"><p:cBhvr><p:cTn id="37" dur="1000"/><p:tgtEl><p:spTgt spid="249"/></p:tgtEl></p:cBhvr></p:animEffect><p:anim calcmode="lin" valueType="num"><p:cBhvr><p:cTn id="38" dur="1000" fill="hold"/><p:tgtEl><p:spTgt spid="249"/></p:tgtEl><p:attrNameLst><p:attrName>ppt_x</p:attrName></p:attrNameLst></p:cBhvr><p:tavLst><p:tav tm="0"><p:val><p:strVal val="#ppt_x"/></p:val></p:tav><p:tav tm="100000"><p:val><p:strVal val="#ppt_x"/></p:val></p:tav></p:tavLst></p:anim><p:anim calcmode="lin" valueType="num"><p:cBhvr><p:cTn id="39" dur="1000" fill="hold"/><p:tgtEl><p:spTgt spid="249"/></p:tgtEl><p:attrNameLst><p:attrName>ppt_y</p:attrName></p:attrNameLst></p:cBhvr><p:tavLst><p:tav tm="0"><p:val><p:strVal val="#ppt_y-.1"/></p:val></p:tav><p:tav tm="100000"><p:val><p:strVal val="#ppt_y"/></p:val></p:tav></p:tavLst></p:anim></p:childTnLst></p:cTn></p:par></p:childTnLst></p:cTn></p:par></p:childTnLst></p:cTn></p:par><p:par><p:cTn id="40" fill="hold"><p:stCondLst><p:cond delay="indefinite"/></p:stCondLst><p:childTnLst><p:par><p:cTn id="41" fill="hold"><p:stCondLst><p:cond delay="0"/></p:stCondLst><p:childTnLst><p:par><p:cTn id="42" presetID="10" presetClass="exit" presetSubtype="0" fill="hold" grpId="1" nodeType="clickEffect"><p:stCondLst><p:cond delay="0"/></p:stCondLst><p:childTnLst><p:animEffect transition="out" filter="fade"><p:cBhvr><p:cTn id="43" dur="500"/><p:tgtEl><p:spTgt spid="5"/></p:tgtEl></p:cBhvr></p:animEffect><p:set><p:cBhvr><p:cTn id="44" dur="1" fill="hold"><p:stCondLst><p:cond delay="499"/></p:stCondLst></p:cTn><p:tgtEl><p:spTgt spid="5"/></p:tgtEl><p:attrNameLst><p:attrName>style.visibility</p:attrName></p:attrNameLst></p:cBhvr><p:to><p:strVal val="hidden"/></p:to></p:set></p:childTnLst></p:cTn></p:par><p:par><p:cTn id="45" presetID="10" presetClass="exit" presetSubtype="0" fill="hold" grpId="1" nodeType="withEffect"><p:stCondLst><p:cond delay="0"/></p:stCondLst><p:childTnLst><p:animEffect transition="out" filter="fade"><p:cBhvr><p:cTn id="46" dur="500"/><p:tgtEl><p:spTgt spid="234"/></p:tgtEl></p:cBhvr></p:animEffect><p:set><p:cBhvr><p:cTn id="47" dur="1" fill="hold"><p:stCondLst><p:cond delay="499"/></p:stCondLst></p:cTn><p:tgtEl><p:spTgt spid="234"/></p:tgtEl><p:attrNameLst><p:attrName>style.visibility</p:attrName></p:attrNameLst></p:cBhvr><p:to><p:strVal val="hidden"/></p:to></p:set></p:childTnLst></p:cTn></p:par><p:par><p:cTn id="48" presetID="10" presetClass="exit" presetSubtype="0" fill="hold" grpId="1" nodeType="withEffect"><p:stCondLst><p:cond delay="0"/></p:stCondLst><p:childTnLst><p:animEffect transition="out" filter="fade"><p:cBhvr><p:cTn id="49" dur="500"/><p:tgtEl><p:spTgt spid="237"/></p:tgtEl></p:cBhvr></p:animEffect><p:set><p:cBhvr><p:cTn id="50" dur="1" fill="hold"><p:stCondLst><p:cond delay="499"/></p:stCondLst></p:cTn><p:tgtEl><p:spTgt spid="237"/></p:tgtEl><p:attrNameLst><p:attrName>style.visibility</p:attrName></p:attrNameLst></p:cBhvr><p:to><p:strVal val="hidden"/></p:to></p:set></p:childTnLst></p:cTn></p:par><p:par><p:cTn id="51" presetID="10" presetClass="exit" presetSubtype="0" fill="hold" grpId="1" nodeType="withEffect"><p:stCondLst><p:cond delay="0"/></p:stCondLst><p:childTnLst><p:animEffect transition="out" filter="fade"><p:cBhvr><p:cTn id="52" dur="500"/><p:tgtEl><p:spTgt spid="240"/></p:tgtEl></p:cBhvr></p:animEffect><p:set><p:cBhvr><p:cTn id="53" dur="1" fill="hold"><p:stCondLst><p:cond delay="499"/></p:stCondLst></p:cTn><p:tgtEl><p:spTgt spid="240"/></p:tgtEl><p:attrNameLst><p:attrName>style.visibility</p:attrName></p:attrNameLst></p:cBhvr><p:to><p:strVal val="hidden"/></p:to></p:set></p:childTnLst></p:cTn></p:par><p:par><p:cTn id="54" presetID="10" presetClass="exit" presetSubtype="0" fill="hold" grpId="1" nodeType="withEffect"><p:stCondLst><p:cond delay="0"/></p:stCondLst><p:childTnLst><p:animEffect transition="out" filter="fade"><p:cBhvr><p:cTn id="55" dur="500"/><p:tgtEl><p:spTgt spid="246"/></p:tgtEl></p:cBhvr></p:animEffect><p:set><p:cBhvr><p:cTn id="56" dur="1" fill="hold"><p:stCondLst><p:cond delay="499"/></p:stCondLst></p:cTn><p:tgtEl><p:spTgt spid="246"/></p:tgtEl><p:attrNameLst><p:attrName>style.visibility</p:attrName></p:attrNameLst></p:cBhvr><p:to><p:strVal val="hidden"/></p:to></p:set></p:childTnLst></p:cTn></p:par><p:par><p:cTn id="57" presetID="10" presetClass="exit" presetSubtype="0" fill="hold" grpId="1" nodeType="withEffect"><p:stCondLst><p:cond delay="0"/></p:stCondLst><p:childTnLst><p:animEffect transition="out" filter="fade"><p:cBhvr><p:cTn id="58" dur="500"/><p:tgtEl><p:spTgt spid="249"/></p:tgtEl></p:cBhvr></p:animEffect><p:set><p:cBhvr><p:cTn id="59" dur="1" fill="hold"><p:stCondLst><p:cond delay="499"/></p:stCondLst></p:cTn><p:tgtEl><p:spTgt spid="249"/></p:tgtEl><p:attrNameLst><p:attrName>style.visibility</p:attrName></p:attrNameLst></p:cBhvr><p:to><p:strVal val="hidden"/></p:to></p:set></p:childTnLst></p:cTn></p:par></p:childTnLst></p:cTn></p:par><p:par><p:cTn id="60" fill="hold"><p:stCondLst><p:cond delay="500"/></p:stCondLst><p:childTnLst><p:par><p:cTn id="61" presetID="26" presetClass="emph" presetSubtype="0" repeatCount="3000" fill="hold" grpId="1" nodeType="afterEffect"><p:stCondLst><p:cond delay="0"/></p:stCondLst><p:childTnLst><p:animEffect transition="out" filter="fade"><p:cBhvr><p:cTn id="62" dur="500" tmFilter="0, 0; .2, .5; .8, .5; 1, 0"/><p:tgtEl><p:spTgt spid="243"/></p:tgtEl></p:cBhvr></p:animEffect><p:animScale><p:cBhvr><p:cTn id="63" dur="250" autoRev="1" fill="hold"/><p:tgtEl><p:spTgt spid="243"/></p:tgtEl></p:cBhvr><p:by x="105000" y="105000"/></p:animScale></p:childTnLst></p:cTn></p:par></p:childTnLst></p:cTn></p:par></p:childTnLst></p:cTn></p:par><p:par><p:cTn id="64" fill="hold"><p:stCondLst><p:cond delay="indefinite"/></p:stCondLst><p:childTnLst><p:par><p:cTn id="65" fill="hold"><p:stCondLst><p:cond delay="0"/></p:stCondLst><p:childTnLst><p:par><p:cTn id="66" presetID="10" presetClass="exit" presetSubtype="0" fill="hold" grpId="2" nodeType="clickEffect"><p:stCondLst><p:cond delay="0"/></p:stCondLst><p:childTnLst><p:animEffect transition="out" filter="fade"><p:cBhvr><p:cTn id="67" dur="500"/><p:tgtEl><p:spTgt spid="243"/></p:tgtEl></p:cBhvr></p:animEffect><p:set><p:cBhvr><p:cTn id="68" dur="1" fill="hold"><p:stCondLst><p:cond delay="499"/></p:stCondLst></p:cTn><p:tgtEl><p:spTgt spid="243"/></p:tgtEl><p:attrNameLst><p:attrName>style.visibility</p:attrName></p:attrNameLst></p:cBhvr><p:to><p:strVal val="hidden"/></p:to></p:set></p:childTnLst></p:cTn></p:par></p:childTnLst></p:cTn></p:par><p:par><p:cTn id="69" fill="hold"><p:stCondLst><p:cond delay="500"/></p:stCondLst><p:childTnLst><p:par><p:cTn id="70" presetID="2" presetClass="entr" presetSubtype="1" accel="30000" fill="hold" nodeType="afterEffect" p14:presetBounceEnd="42000"><p:stCondLst><p:cond delay="0"/></p:stCondLst><p:childTnLst><p:set><p:cBhvr><p:cTn id="71" dur="1" fill="hold"><p:stCondLst><p:cond delay="0"/></p:stCondLst></p:cTn><p:tgtEl><p:spTgt spid="55"/></p:tgtEl><p:attrNameLst><p:attrName>style.visibility</p:attrName></p:attrNameLst></p:cBhvr><p:to><p:strVal val="visible"/></p:to></p:set><p:anim calcmode="lin" valueType="num" p14:bounceEnd="42000"><p:cBhvr additive="base"><p:cTn id="72" dur="500" fill="hold"/><p:tgtEl><p:spTgt spid="55"/></p:tgtEl><p:attrNameLst><p:attrName>ppt_x</p:attrName></p:attrNameLst></p:cBhvr><p:tavLst><p:tav tm="0"><p:val><p:strVal val="#ppt_x"/></p:val></p:tav><p:tav tm="100000"><p:val><p:strVal val="#ppt_x"/></p:val></p:tav></p:tavLst></p:anim><p:anim calcmode="lin" valueType="num" p14:bounceEnd="42000"><p:cBhvr additive="base"><p:cTn id="73" dur="500" fill="hold"/><p:tgtEl><p:spTgt spid="55"/></p:tgtEl><p:attrNameLst><p:attrName>ppt_y</p:attrName></p:attrNameLst></p:cBhvr><p:tavLst><p:tav tm="0"><p:val><p:strVal val="0-#ppt_h/2"/></p:val></p:tav><p:tav tm="100000"><p:val><p:strVal val="#ppt_y"/></p:val></p:tav></p:tavLst></p:anim></p:childTnLst><p:subTnLst><p:audio><p:cMediaNode><p:cTn display="0" masterRel="sameClick"><p:stCondLst><p:cond evt="begin" delay="0"><p:tn val="70"/></p:cond></p:stCondLst><p:endCondLst><p:cond evt="onStopAudio" delay="0"><p:tgtEl><p:sldTgt/></p:tgtEl></p:cond></p:endCondLst></p:cTn><p:tgtEl><p:sndTgt r:embed="rId3" name="Connect 4 SFX.wav"/></p:tgtEl></p:cMediaNode></p:audio></p:subTnLst></p:cTn></p:par></p:childTnLst></p:cTn></p:par></p:childTnLst></p:cTn></p:par></p:childTnLst></p:cTn><p:prevCondLst><p:cond evt="onPrev" delay="0"><p:tgtEl><p:sldTgt/></p:tgtEl></p:cond></p:prevCondLst><p:nextCondLst><p:cond evt="onNext" delay="0"><p:tgtEl><p:sldTgt/></p:tgtEl></p:cond></p:nextCondLst></p:seq></p:childTnLst></p:cTn></p:par></p:tnLst><p:bldLst><p:bldP spid="5" grpId="0" animBg="1"/><p:bldP spid="5" grpId="1" animBg="1"/><p:bldP spid="234" grpId="0" animBg="1"/><p:bldP spid="234" grpId="1" animBg="1"/><p:bldP spid="237" grpId="0" animBg="1"/><p:bldP spid="237" grpId="1" animBg="1"/><p:bldP spid="240" grpId="0" animBg="1"/><p:bldP spid="240" grpId="1" animBg="1"/><p:bldP spid="243" grpId="0" animBg="1"/><p:bldP spid="243" grpId="1" animBg="1"/><p:bldP spid="243" grpId="2" animBg="1"/><p:bldP spid="246" grpId="0" animBg="1"/><p:bldP spid="246" grpId="1" animBg="1"/><p:bldP spid="249" grpId="0" animBg="1"/><p:bldP spid="249" grpId="1" animBg="1"/></p:bldLst></p:timing></mc:Choice><mc:Fallback xmlns=""><p:timing><p:tnLst><p:par><p:cTn id="1" dur="indefinite" restart="never" nodeType="tmRoot"><p:childTnLst><p:seq concurrent="1" nextAc="seek"><p:cTn id="2" dur="indefinite" nodeType="mainSeq"><p:childTnLst><p:par><p:cTn id="3" fill="hold"><p:stCondLst><p:cond delay="indefinite"/><p:cond evt="onBegin" delay="0"><p:tn val="2"/></p:cond></p:stCondLst><p:childTnLst><p:par><p:cTn id="4" fill="hold"><p:stCondLst><p:cond delay="0"/></p:stCondLst><p:childTnLst><p:par><p:cTn id="5" presetID="47" presetClass="entr" presetSubtype="0" fill="hold" grpId="0" nodeType="withEffect"><p:stCondLst><p:cond delay="0"/></p:stCondLst><p:childTnLst><p:set><p:cBhvr><p:cTn id="6" dur="1" fill="hold"><p:stCondLst><p:cond delay="0"/></p:stCondLst></p:cTn><p:tgtEl><p:spTgt spid="5"/></p:tgtEl><p:attrNameLst><p:attrName>style.visibility</p:attrName></p:attrNameLst></p:cBhvr><p:to><p:strVal val="visible"/></p:to></p:set><p:animEffect transition="in" filter="fade"><p:cBhvr><p:cTn id="7" dur="1000"/><p:tgtEl><p:spTgt spid="5"/></p:tgtEl></p:cBhvr></p:animEffect><p:anim calcmode="lin" valueType="num"><p:cBhvr><p:cTn id="8" dur="1000" fill="hold"/><p:tgtEl><p:spTgt spid="5"/></p:tgtEl><p:attrNameLst><p:attrName>ppt_x</p:attrName></p:attrNameLst></p:cBhvr><p:tavLst><p:tav tm="0"><p:val><p:strVal val="#ppt_x"/></p:val></p:tav><p:tav tm="100000"><p:val><p:strVal val="#ppt_x"/></p:val></p:tav></p:tavLst></p:anim><p:anim calcmode="lin" valueType="num"><p:cBhvr><p:cTn id="9" dur="1000" fill="hold"/><p:tgtEl><p:spTgt spid="5"/></p:tgtEl><p:attrNameLst><p:attrName>ppt_y</p:attrName></p:attrNameLst></p:cBhvr><p:tavLst><p:tav tm="0"><p:val><p:strVal val="#ppt_y-.1"/></p:val></p:tav><p:tav tm="100000"><p:val><p:strVal val="#ppt_y"/></p:val></p:tav></p:tavLst></p:anim></p:childTnLst></p:cTn></p:par><p:par><p:cTn id="10" presetID="47" presetClass="entr" presetSubtype="0" fill="hold" grpId="0" nodeType="withEffect"><p:stCondLst><p:cond delay="0"/></p:stCondLst><p:childTnLst><p:set><p:cBhvr><p:cTn id="11" dur="1" fill="hold"><p:stCondLst><p:cond delay="0"/></p:stCondLst></p:cTn><p:tgtEl><p:spTgt spid="234"/></p:tgtEl><p:attrNameLst><p:attrName>style.visibility</p:attrName></p:attrNameLst></p:cBhvr><p:to><p:strVal val="visible"/></p:to></p:set><p:animEffect transition="in" filter="fade"><p:cBhvr><p:cTn id="12" dur="1000"/><p:tgtEl><p:spTgt spid="234"/></p:tgtEl></p:cBhvr></p:animEffect><p:anim calcmode="lin" valueType="num"><p:cBhvr><p:cTn id="13" dur="1000" fill="hold"/><p:tgtEl><p:spTgt spid="234"/></p:tgtEl><p:attrNameLst><p:attrName>ppt_x</p:attrName></p:attrNameLst></p:cBhvr><p:tavLst><p:tav tm="0"><p:val><p:strVal val="#ppt_x"/></p:val></p:tav><p:tav tm="100000"><p:val><p:strVal val="#ppt_x"/></p:val></p:tav></p:tavLst></p:anim><p:anim calcmode="lin" valueType="num"><p:cBhvr><p:cTn id="14" dur="1000" fill="hold"/><p:tgtEl><p:spTgt spid="234"/></p:tgtEl><p:attrNameLst><p:attrName>ppt_y</p:attrName></p:attrNameLst></p:cBhvr><p:tavLst><p:tav tm="0"><p:val><p:strVal val="#ppt_y-.1"/></p:val></p:tav><p:tav tm="100000"><p:val><p:strVal val="#ppt_y"/></p:val></p:tav></p:tavLst></p:anim></p:childTnLst></p:cTn></p:par><p:par><p:cTn id="15" presetID="47" presetClass="entr" presetSubtype="0" fill="hold" grpId="0" nodeType="withEffect"><p:stCondLst><p:cond delay="0"/></p:stCondLst><p:childTnLst><p:set><p:cBhvr><p:cTn id="16" dur="1" fill="hold"><p:stCondLst><p:cond delay="0"/></p:stCondLst></p:cTn><p:tgtEl><p:spTgt spid="237"/></p:tgtEl><p:attrNameLst><p:attrName>style.visibility</p:attrName></p:attrNameLst></p:cBhvr><p:to><p:strVal val="visible"/></p:to></p:set><p:animEffect transition="in" filter="fade"><p:cBhvr><p:cTn id="17" dur="1000"/><p:tgtEl><p:spTgt spid="237"/></p:tgtEl></p:cBhvr></p:animEffect><p:anim calcmode="lin" valueType="num"><p:cBhvr><p:cTn id="18" dur="1000" fill="hold"/><p:tgtEl><p:spTgt spid="237"/></p:tgtEl><p:attrNameLst><p:attrName>ppt_x</p:attrName></p:attrNameLst></p:cBhvr><p:tavLst><p:tav tm="0"><p:val><p:strVal val="#ppt_x"/></p:val></p:tav><p:tav tm="100000"><p:val><p:strVal val="#ppt_x"/></p:val></p:tav></p:tavLst></p:anim><p:anim calcmode="lin" valueType="num"><p:cBhvr><p:cTn id="19" dur="1000" fill="hold"/><p:tgtEl><p:spTgt spid="237"/></p:tgtEl><p:attrNameLst><p:attrName>ppt_y</p:attrName></p:attrNameLst></p:cBhvr><p:tavLst><p:tav tm="0"><p:val><p:strVal val="#ppt_y-.1"/></p:val></p:tav><p:tav tm="100000"><p:val><p:strVal val="#ppt_y"/></p:val></p:tav></p:tavLst></p:anim></p:childTnLst></p:cTn></p:par><p:par><p:cTn id="20" presetID="47" presetClass="entr" presetSubtype="0" fill="hold" grpId="0" nodeType="withEffect"><p:stCondLst><p:cond delay="0"/></p:stCondLst><p:childTnLst><p:set><p:cBhvr><p:cTn id="21" dur="1" fill="hold"><p:stCondLst><p:cond delay="0"/></p:stCondLst></p:cTn><p:tgtEl><p:spTgt spid="240"/></p:tgtEl><p:attrNameLst><p:attrName>style.visibility</p:attrName></p:attrNameLst></p:cBhvr><p:to><p:strVal val="visible"/></p:to></p:set><p:animEffect transition="in" filter="fade"><p:cBhvr><p:cTn id="22" dur="1000"/><p:tgtEl><p:spTgt spid="240"/></p:tgtEl></p:cBhvr></p:animEffect><p:anim calcmode="lin" valueType="num"><p:cBhvr><p:cTn id="23" dur="1000" fill="hold"/><p:tgtEl><p:spTgt spid="240"/></p:tgtEl><p:attrNameLst><p:attrName>ppt_x</p:attrName></p:attrNameLst></p:cBhvr><p:tavLst><p:tav tm="0"><p:val><p:strVal val="#ppt_x"/></p:val></p:tav><p:tav tm="100000"><p:val><p:strVal val="#ppt_x"/></p:val></p:tav></p:tavLst></p:anim><p:anim calcmode="lin" valueType="num"><p:cBhvr><p:cTn id="24" dur="1000" fill="hold"/><p:tgtEl><p:spTgt spid="240"/></p:tgtEl><p:attrNameLst><p:attrName>ppt_y</p:attrName></p:attrNameLst></p:cBhvr><p:tavLst><p:tav tm="0"><p:val><p:strVal val="#ppt_y-.1"/></p:val></p:tav><p:tav tm="100000"><p:val><p:strVal val="#ppt_y"/></p:val></p:tav></p:tavLst></p:anim></p:childTnLst></p:cTn></p:par><p:par><p:cTn id="25" presetID="47" presetClass="entr" presetSubtype="0" fill="hold" grpId="0" nodeType="withEffect"><p:stCondLst><p:cond delay="0"/></p:stCondLst><p:childTnLst><p:set><p:cBhvr><p:cTn id="26" dur="1" fill="hold"><p:stCondLst><p:cond delay="0"/></p:stCondLst></p:cTn><p:tgtEl><p:spTgt spid="243"/></p:tgtEl><p:attrNameLst><p:attrName>style.visibility</p:attrName></p:attrNameLst></p:cBhvr><p:to><p:strVal val="visible"/></p:to></p:set><p:animEffect transition="in" filter="fade"><p:cBhvr><p:cTn id="27" dur="1000"/><p:tgtEl><p:spTgt spid="243"/></p:tgtEl></p:cBhvr></p:animEffect><p:anim calcmode="lin" valueType="num"><p:cBhvr><p:cTn id="28" dur="1000" fill="hold"/><p:tgtEl><p:spTgt spid="243"/></p:tgtEl><p:attrNameLst><p:attrName>ppt_x</p:attrName></p:attrNameLst></p:cBhvr><p:tavLst><p:tav tm="0"><p:val><p:strVal val="#ppt_x"/></p:val></p:tav><p:tav tm="100000"><p:val><p:strVal val="#ppt_x"/></p:val></p:tav></p:tavLst></p:anim><p:anim calcmode="lin" valueType="num"><p:cBhvr><p:cTn id="29" dur="1000" fill="hold"/><p:tgtEl><p:spTgt spid="243"/></p:tgtEl><p:attrNameLst><p:attrName>ppt_y</p:attrName></p:attrNameLst></p:cBhvr><p:tavLst><p:tav tm="0"><p:val><p:strVal val="#ppt_y-.1"/></p:val></p:tav><p:tav tm="100000"><p:val><p:strVal val="#ppt_y"/></p:val></p:tav></p:tavLst></p:anim></p:childTnLst></p:cTn></p:par><p:par><p:cTn id="30" presetID="47" presetClass="entr" presetSubtype="0" fill="hold" grpId="0" nodeType="withEffect"><p:stCondLst><p:cond delay="0"/></p:stCondLst><p:childTnLst><p:set><p:cBhvr><p:cTn id="31" dur="1" fill="hold"><p:stCondLst><p:cond delay="0"/></p:stCondLst></p:cTn><p:tgtEl><p:spTgt spid="246"/></p:tgtEl><p:attrNameLst><p:attrName>style.visibility</p:attrName></p:attrNameLst></p:cBhvr><p:to><p:strVal val="visible"/></p:to></p:set><p:animEffect transition="in" filter="fade"><p:cBhvr><p:cTn id="32" dur="1000"/><p:tgtEl><p:spTgt spid="246"/></p:tgtEl></p:cBhvr></p:animEffect><p:anim calcmode="lin" valueType="num"><p:cBhvr><p:cTn id="33" dur="1000" fill="hold"/><p:tgtEl><p:spTgt spid="246"/></p:tgtEl><p:attrNameLst><p:attrName>ppt_x</p:attrName></p:attrNameLst></p:cBhvr><p:tavLst><p:tav tm="0"><p:val><p:strVal val="#ppt_x"/></p:val></p:tav><p:tav tm="100000"><p:val><p:strVal val="#ppt_x"/></p:val></p:tav></p:tavLst></p:anim><p:anim calcmode="lin" valueType="num"><p:cBhvr><p:cTn id="34" dur="1000" fill="hold"/><p:tgtEl><p:spTgt spid="246"/></p:tgtEl><p:attrNameLst><p:attrName>ppt_y</p:attrName></p:attrNameLst></p:cBhvr><p:tavLst><p:tav tm="0"><p:val><p:strVal val="#ppt_y-.1"/></p:val></p:tav><p:tav tm="100000"><p:val><p:strVal val="#ppt_y"/></p:val></p:tav></p:tavLst></p:anim></p:childTnLst></p:cTn></p:par><p:par><p:cTn id="35" presetID="47" presetClass="entr" presetSubtype="0" fill="hold" grpId="0" nodeType="withEffect"><p:stCondLst><p:cond delay="0"/></p:stCondLst><p:childTnLst><p:set><p:cBhvr><p:cTn id="36" dur="1" fill="hold"><p:stCondLst><p:cond delay="0"/></p:stCondLst></p:cTn><p:tgtEl><p:spTgt spid="249"/></p:tgtEl><p:attrNameLst><p:attrName>style.visibility</p:attrName></p:attrNameLst></p:cBhvr><p:to><p:strVal val="visible"/></p:to></p:set><p:animEffect transition="in" filter="fade"><p:cBhvr><p:cTn id="37" dur="1000"/><p:tgtEl><p:spTgt spid="249"/></p:tgtEl></p:cBhvr></p:animEffect><p:anim calcmode="lin" valueType="num"><p:cBhvr><p:cTn id="38" dur="1000" fill="hold"/><p:tgtEl><p:spTgt spid="249"/></p:tgtEl><p:attrNameLst><p:attrName>ppt_x</p:attrName></p:attrNameLst></p:cBhvr><p:tavLst><p:tav tm="0"><p:val><p:strVal val="#ppt_x"/></p:val></p:tav><p:tav tm="100000"><p:val><p:strVal val="#ppt_x"/></p:val></p:tav></p:tavLst></p:anim><p:anim calcmode="lin" valueType="num"><p:cBhvr><p:cTn id="39" dur="1000" fill="hold"/><p:tgtEl><p:spTgt spid="249"/></p:tgtEl><p:attrNameLst><p:attrName>ppt_y</p:attrName></p:attrNameLst></p:cBhvr><p:tavLst><p:tav tm="0"><p:val><p:strVal val="#ppt_y-.1"/></p:val></p:tav><p:tav tm="100000"><p:val><p:strVal val="#ppt_y"/></p:val></p:tav></p:tavLst></p:anim></p:childTnLst></p:cTn></p:par></p:childTnLst></p:cTn></p:par></p:childTnLst></p:cTn></p:par><p:par><p:cTn id="40" fill="hold"><p:stCondLst><p:cond delay="indefinite"/></p:stCondLst><p:childTnLst><p:par><p:cTn id="41" fill="hold"><p:stCondLst><p:cond delay="0"/></p:stCondLst><p:childTnLst><p:par><p:cTn id="42" presetID="10" presetClass="exit" presetSubtype="0" fill="hold" grpId="1" nodeType="clickEffect"><p:stCondLst><p:cond delay="0"/></p:stCondLst><p:childTnLst><p:animEffect transition="out" filter="fade"><p:cBhvr><p:cTn id="43" dur="500"/><p:tgtEl><p:spTgt spid="5"/></p:tgtEl></p:cBhvr></p:animEffect><p:set><p:cBhvr><p:cTn id="44" dur="1" fill="hold"><p:stCondLst><p:cond delay="499"/></p:stCondLst></p:cTn><p:tgtEl><p:spTgt spid="5"/></p:tgtEl><p:attrNameLst><p:attrName>style.visibility</p:attrName></p:attrNameLst></p:cBhvr><p:to><p:strVal val="hidden"/></p:to></p:set></p:childTnLst></p:cTn></p:par><p:par><p:cTn id="45" presetID="10" presetClass="exit" presetSubtype="0" fill="hold" grpId="1" nodeType="withEffect"><p:stCondLst><p:cond delay="0"/></p:stCondLst><p:childTnLst><p:animEffect transition="out" filter="fade"><p:cBhvr><p:cTn id="46" dur="500"/><p:tgtEl><p:spTgt spid="234"/></p:tgtEl></p:cBhvr></p:animEffect><p:set><p:cBhvr><p:cTn id="47" dur="1" fill="hold"><p:stCondLst><p:cond delay="499"/></p:stCondLst></p:cTn><p:tgtEl><p:spTgt spid="234"/></p:tgtEl><p:attrNameLst><p:attrName>style.visibility</p:attrName></p:attrNameLst></p:cBhvr><p:to><p:strVal val="hidden"/></p:to></p:set></p:childTnLst></p:cTn></p:par><p:par><p:cTn id="48" presetID="10" presetClass="exit" presetSubtype="0" fill="hold" grpId="1" nodeType="withEffect"><p:stCondLst><p:cond delay="0"/></p:stCondLst><p:childTnLst><p:animEffect transition="out" filter="fade"><p:cBhvr><p:cTn id="49" dur="500"/><p:tgtEl><p:spTgt spid="237"/></p:tgtEl></p:cBhvr></p:animEffect><p:set><p:cBhvr><p:cTn id="50" dur="1" fill="hold"><p:stCondLst><p:cond delay="499"/></p:stCondLst></p:cTn><p:tgtEl><p:spTgt spid="237"/></p:tgtEl><p:attrNameLst><p:attrName>style.visibility</p:attrName></p:attrNameLst></p:cBhvr><p:to><p:strVal val="hidden"/></p:to></p:set></p:childTnLst></p:cTn></p:par><p:par><p:cTn id="51" presetID="10" presetClass="exit" presetSubtype="0" fill="hold" grpId="1" nodeType="withEffect"><p:stCondLst><p:cond delay="0"/></p:stCondLst><p:childTnLst><p:animEffect transition="out" filter="fade"><p:cBhvr><p:cTn id="52" dur="500"/><p:tgtEl><p:spTgt spid="240"/></p:tgtEl></p:cBhvr></p:animEffect><p:set><p:cBhvr><p:cTn id="53" dur="1" fill="hold"><p:stCondLst><p:cond delay="499"/></p:stCondLst></p:cTn><p:tgtEl><p:spTgt spid="240"/></p:tgtEl><p:attrNameLst><p:attrName>style.visibility</p:attrName></p:attrNameLst></p:cBhvr><p:to><p:strVal val="hidden"/></p:to></p:set></p:childTnLst></p:cTn></p:par><p:par><p:cTn id="54" presetID="10" presetClass="exit" presetSubtype="0" fill="hold" grpId="1" nodeType="withEffect"><p:stCondLst><p:cond delay="0"/></p:stCondLst><p:childTnLst><p:animEffect transition="out" filter="fade"><p:cBhvr><p:cTn id="55" dur="500"/><p:tgtEl><p:spTgt spid="246"/></p:tgtEl></p:cBhvr></p:animEffect><p:set><p:cBhvr><p:cTn id="56" dur="1" fill="hold"><p:stCondLst><p:cond delay="499"/></p:stCondLst></p:cTn><p:tgtEl><p:spTgt spid="246"/></p:tgtEl><p:attrNameLst><p:attrName>style.visibility</p:attrName></p:attrNameLst></p:cBhvr><p:to><p:strVal val="hidden"/></p:to></p:set></p:childTnLst></p:cTn></p:par><p:par><p:cTn id="57" presetID="10" presetClass="exit" presetSubtype="0" fill="hold" grpId="1" nodeType="withEffect"><p:stCondLst><p:cond delay="0"/></p:stCondLst><p:childTnLst><p:animEffect transition="out" filter="fade"><p:cBhvr><p:cTn id="58" dur="500"/><p:tgtEl><p:spTgt spid="249"/></p:tgtEl></p:cBhvr></p:animEffect><p:set><p:cBhvr><p:cTn id="59" dur="1" fill="hold"><p:stCondLst><p:cond delay="499"/></p:stCondLst></p:cTn><p:tgtEl><p:spTgt spid="249"/></p:tgtEl><p:attrNameLst><p:attrName>style.visibility</p:attrName></p:attrNameLst></p:cBhvr><p:to><p:strVal val="hidden"/></p:to></p:set></p:childTnLst></p:cTn></p:par></p:childTnLst></p:cTn></p:par><p:par><p:cTn id="60" fill="hold"><p:stCondLst><p:cond delay="500"/></p:stCondLst><p:childTnLst><p:par><p:cTn id="61" presetID="26" presetClass="emph" presetSubtype="0" repeatCount="3000" fill="hold" grpId="1" nodeType="afterEffect"><p:stCondLst><p:cond delay="0"/></p:stCondLst><p:childTnLst><p:animEffect transition="out" filter="fade"><p:cBhvr><p:cTn id="62" dur="500" tmFilter="0, 0; .2, .5; .8, .5; 1, 0"/><p:tgtEl><p:spTgt spid="243"/></p:tgtEl></p:cBhvr></p:animEffect><p:animScale><p:cBhvr><p:cTn id="63" dur="250" autoRev="1" fill="hold"/><p:tgtEl><p:spTgt spid="243"/></p:tgtEl></p:cBhvr><p:by x="105000" y="105000"/></p:animScale></p:childTnLst></p:cTn></p:par></p:childTnLst></p:cTn></p:par></p:childTnLst></p:cTn></p:par><p:par><p:cTn id="64" fill="hold"><p:stCondLst><p:cond delay="indefinite"/></p:stCondLst><p:childTnLst><p:par><p:cTn id="65" fill="hold"><p:stCondLst><p:cond delay="0"/></p:stCondLst><p:childTnLst><p:par><p:cTn id="66" presetID="10" presetClass="exit" presetSubtype="0" fill="hold" grpId="2" nodeType="clickEffect"><p:stCondLst><p:cond delay="0"/></p:stCondLst><p:childTnLst><p:animEffect transition="out" filter="fade"><p:cBhvr><p:cTn id="67" dur="500"/><p:tgtEl><p:spTgt spid="243"/></p:tgtEl></p:cBhvr></p:animEffect><p:set><p:cBhvr><p:cTn id="68" dur="1" fill="hold"><p:stCondLst><p:cond delay="499"/></p:stCondLst></p:cTn><p:tgtEl><p:spTgt spid="243"/></p:tgtEl><p:attrNameLst><p:attrName>style.visibility</p:attrName></p:attrNameLst></p:cBhvr><p:to><p:strVal val="hidden"/></p:to></p:set></p:childTnLst></p:cTn></p:par></p:childTnLst></p:cTn></p:par><p:par><p:cTn id="69" fill="hold"><p:stCondLst><p:cond delay="500"/></p:stCondLst><p:childTnLst><p:par><p:cTn id="70" presetID="2" presetClass="entr" presetSubtype="1" accel="30000" fill="hold" nodeType="afterEffect"><p:stCondLst><p:cond delay="0"/></p:stCondLst><p:childTnLst><p:set><p:cBhvr><p:cTn id="71" dur="1" fill="hold"><p:stCondLst><p:cond delay="0"/></p:stCondLst></p:cTn><p:tgtEl><p:spTgt spid="55"/></p:tgtEl><p:attrNameLst><p:attrName>style.visibility</p:attrName></p:attrNameLst></p:cBhvr><p:to><p:strVal val="visible"/></p:to></p:set><p:anim calcmode="lin" valueType="num"><p:cBhvr additive="base"><p:cTn id="72" dur="500" fill="hold"/><p:tgtEl><p:spTgt spid="55"/></p:tgtEl><p:attrNameLst><p:attrName>ppt_x</p:attrName></p:attrNameLst></p:cBhvr><p:tavLst><p:tav tm="0"><p:val><p:strVal val="#ppt_x"/></p:val></p:tav><p:tav tm="100000"><p:val><p:strVal val="#ppt_x"/></p:val></p:tav></p:tavLst></p:anim><p:anim calcmode="lin" valueType="num"><p:cBhvr additive="base"><p:cTn id="73" dur="500" fill="hold"/><p:tgtEl><p:spTgt spid="55"/></p:tgtEl><p:attrNameLst><p:attrName>ppt_y</p:attrName></p:attrNameLst></p:cBhvr><p:tavLst><p:tav tm="0"><p:val><p:strVal val="0-#ppt_h/2"/></p:val></p:tav><p:tav tm="100000"><p:val><p:strVal val="#ppt_y"/></p:val></p:tav></p:tavLst></p:anim></p:childTnLst><p:subTnLst><p:audio><p:cMediaNode><p:cTn display="0" masterRel="sameClick"><p:stCondLst><p:cond evt="begin" delay="0"><p:tn val="70"/></p:cond></p:stCondLst><p:endCondLst><p:cond evt="onStopAudio" delay="0"><p:tgtEl><p:sldTgt/></p:tgtEl></p:cond></p:endCondLst></p:cTn><p:tgtEl><p:sndTgt r:embed="rId7" name="Connect 4 SFX.wav"/></p:tgtEl></p:cMediaNode></p:audio></p:subTnLst></p:cTn></p:par></p:childTnLst></p:cTn></p:par></p:childTnLst></p:cTn></p:par></p:childTnLst></p:cTn><p:prevCondLst><p:cond evt="onPrev" delay="0"><p:tgtEl><p:sldTgt/></p:tgtEl></p:cond></p:prevCondLst><p:nextCondLst><p:cond evt="onNext" delay="0"><p:tgtEl><p:sldTgt/></p:tgtEl></p:cond></p:nextCondLst></p:seq></p:childTnLst></p:cTn></p:par></p:tnLst><p:bldLst><p:bldP spid="5" grpId="0" animBg="1"/><p:bldP spid="5" grpId="1" animBg="1"/><p:bldP spid="234" grpId="0" animBg="1"/><p:bldP spid="234" grpId="1" animBg="1"/><p:bldP spid="237" grpId="0" animBg="1"/><p:bldP spid="237" grpId="1" animBg="1"/><p:bldP spid="240" grpId="0" animBg="1"/><p:bldP spid="240" grpId="1" animBg="1"/><p:bldP spid="243" grpId="0" animBg="1"/><p:bldP spid="243" grpId="1" animBg="1"/><p:bldP spid="243" grpId="2" animBg="1"/><p:bldP spid="246" grpId="0" animBg="1"/><p:bldP spid="246" grpId="1" animBg="1"/><p:bldP spid="249" grpId="0" animBg="1"/><p:bldP spid="249" grpId="1" animBg="1"/></p:bldLst></p:timing></mc:Fallback></mc:AlternateContent></p:sld>